{
    "caption": "2023-10",
    "members": [
        {
            "id": "6",
            "name": "玉露っちゃ",
            "sales": 154131
        },
        {
            "id": "3",
            "name": "右衛門",
            "sales": 144426
        },
        {
            "id": "4",
            "name": "カテキン茶",
            "sales": 141912
        },
        {
            "id": "5",
            "name": "お生茶",
            "sales": 139929
        },
        {
            "id": "10",
            "name": "カルパスウォーター",
            "sales": 132496
        },
        {
            "id": "9",
            "name": "バーヤリスアップル",
            "sales": 125456
        },
        {
            "id": "11",
            "name": "ワンワ金の微糖",
            "sales": 121521
        },
        {
            "id": "2",
            "name": "わーい濃茶",
            "sales": 119950
        },
        {
            "id": "20",
            "name": "パプシコーラゼロ",
            "sales": 112770
        },
        {
            "id": "7",
            "name": "にごる茶",
            "sales": 108568
        },
        {
            "id": "17",
            "name": "コッコーラ",
            "sales": 107767
        },
        {
            "id": "15",
            "name": "フォンタメロン",
            "sales": 107648
        },
        {
            "id": "26",
            "name": "ポスブレンド",
            "sales": 107448
        },
        {
            "id": "30",
            "name": "アップルティー",
            "sales": 106134
        },
        {
            "id": "27",
            "name": "ポスカフェオレ",
            "sales": 101828
        },
        {
            "id": "12",
            "name": "ワンワブラック",
            "sales": 101536
        },
        {
            "id": "14",
            "name": "フォンタオレンジ",
            "sales": 99724
        },
        {
            "id": "25",
            "name": "ポスブラック",
            "sales": 99718
        },
        {
            "id": "19",
            "name": "パプシコーラ",
            "sales": 99601
        },
        {
            "id": "29",
            "name": "レモーネ紅茶",
            "sales": 99323
        },
        {
            "id": "21",
            "name": "ななちゃん",
            "sales": 98987
        },
        {
            "id": "16",
            "name": "サプライト",
            "sales": 98470
        },
        {
            "id": "8",
            "name": "バーヤリスオレンジ",
            "sales": 97013
        },
        {
            "id": "1",
            "name": "わーい緑茶",
            "sales": 96719
        },
        {
            "id": "13",
            "name": "フォンタグレープ",
            "sales": 96577
        },
        {
            "id": "46",
            "name": "ポッカリスエット",
            "sales": 96555
        },
        {
            "id": "0",
            "name": "わーいお茶",
            "sales": 95693
        },
        {
            "id": "23",
            "name": "アセルラドリンク",
            "sales": 95229
        },
        {
            "id": "22",
            "name": "Gakuri",
            "sales": 94556
        },
        {
            "id": "24",
            "name": "はちむつレモン",
            "sales": 94206
        },
        {
            "id": "38",
            "name": "ジャージアブラック",
            "sales": 92821
        },
        {
            "id": "28",
            "name": "トロピカルレモン",
            "sales": 90642
        },
        {
            "id": "37",
            "name": "ジャージア微糖",
            "sales": 87796
        },
        {
            "id": "31",
            "name": "紅茶花壇",
            "sales": 85666
        },
        {
            "id": "35",
            "name": "スーコル",
            "sales": 85399
        },
        {
            "id": "33",
            "name": "松屋サイダー",
            "sales": 85216
        },
        {
            "id": "40",
            "name": "メロンソーダ",
            "sales": 84936
        },
        {
            "id": "34",
            "name": "キリリレモン",
            "sales": 84787
        },
        {
            "id": "48",
            "name": "アクアリアス",
            "sales": 84352
        },
        {
            "id": "18",
            "name": "コッコーラゼロ",
            "sales": 83823
        },
        {
            "id": "36",
            "name": "ジャージアコーヒー",
            "sales": 83545
        },
        {
            "id": "32",
            "name": "オレンジーナ",
            "sales": 83321
        },
        {
            "id": "45",
            "name": "KA・RA・DA",
            "sales": 83137
        },
        {
            "id": "43",
            "name": "抹茶ラテ",
            "sales": 79882
        },
        {
            "id": "42",
            "name": "練乳イチゴ",
            "sales": 77746
        },
        {
            "id": "47",
            "name": "午前の紅茶",
            "sales": 77028
        },
        {
            "id": "44",
            "name": "リアルゴール",
            "sales": 75405
        },
        {
            "id": "39",
            "name": "濃いミカン",
            "sales": 71939
        },
        {
            "id": "41",
            "name": "おいしい葡萄",
            "sales": 71763
        },
        {
            "id": "49",
            "name": "カルパスオレンジ",
            "sales": 67652
        }
    ]
}